[
    { "id": "/m/04rlf", "topic": "Music", "parent": true },
    { "id": "/m/02mscn", "topic": "Christian music", "parent_topic": "/m/04rlf" },
    { "id": "/m/0ggq0m", "topic": "Classical music", "parent_topic": "/m/04rlf" },
    { "id": "/m/01lyv", "topic": "Country", "parent_topic": "/m/04rlf" },
    { "id": "/m/02lkt", "topic": "Electronic music", "parent_topic": "/m/04rlf" },
    { "id": "/m/0glt670", "topic": "Hip hop music", "parent_topic": "/m/04rlf" },
    { "id": "/m/05rwpb", "topic": "Independent music", "parent_topic": "/m/04rlf" },
    { "id": "/m/03_d0", "topic": "Jazz", "parent_topic": "/m/04rlf" },
    { "id": "/m/028sqc", "topic": "Music of Asia", "parent_topic": "/m/04rlf" },
    { "id": "/m/0g293", "topic": "Music of Latin America", "parent_topic": "/m/04rlf" },
    { "id": "/m/064t9", "topic": "Pop music", "parent_topic": "/m/04rlf" },
    { "id": "/m/06cqb", "topic": "Reggae", "parent_topic": "/m/04rlf" },
    { "id": "/m/06j6l", "topic": "Rhythm and blues", "parent_topic": "/m/04rlf" },
    { "id": "/m/06by7", "topic": "Rock music", "parent_topic": "/m/04rlf" },
    { "id": "/m/0gywn", "topic": "Soul music", "parent_topic": "/m/04rlf" },

    { "id": "/m/0bzvm2", "topic": "Gaming", "parent": true },
    { "id": "/m/025zzc", "topic": "Action game", "parent_topic": "/m/0bzvm2" },
    { "id": "/m/02ntfj", "topic": "Action-adventure game", "parent_topic": "/m/0bzvm2" },
    { "id": "/m/0b1vjn", "topic": "Casual game", "parent_topic": "/m/0bzvm2" },
    { "id": "/m/02hygl", "topic": "Music video game", "parent_topic": "/m/0bzvm2" },
    { "id": "/m/04q1x3q", "topic": "Puzzle video game", "parent_topic": "/m/0bzvm2" },
    { "id": "/m/01sjng", "topic": "Racing video game", "parent_topic": "/m/0bzvm2" },
    { "id": "/m/0403l3g", "topic": "Role-playing video game", "parent_topic": "/m/0bzvm2" },
    { "id": "/m/021bp2", "topic": "Simulation video game", "parent_topic": "/m/0bzvm2" },
    { "id": "/m/022dc6", "topic": "Sports game", "parent_topic": "/m/0bzvm2" },
    { "id": "/m/03hf_rm", "topic": "Strategy video game", "parent_topic": "/m/0bzvm2" },

    { "id": "/m/06ntj", "topic": "Sports", "parent": true },
    { "id": "/m/0jm_", "topic": "American football", "parent_topic": "/m/06ntj" },
    { "id": "/m/018jz", "topic": "Baseball", "parent_topic": "/m/06ntj" },
    { "id": "/m/018w8", "topic": "Basketball", "parent_topic": "/m/06ntj" },
    { "id": "/m/01cgz", "topic": "Boxing", "parent_topic": "/m/06ntj" },
    { "id": "/m/09xp_", "topic": "Cricket", "parent_topic": "/m/06ntj" },
    { "id": "/m/02vx4", "topic": "Football", "parent_topic": "/m/06ntj" },
    { "id": "/m/037hz", "topic": "Golf", "parent_topic": "/m/06ntj" },
    { "id": "/m/03tmr", "topic": "Ice hockey", "parent_topic": "/m/06ntj" },
    { "id": "/m/01h7lh", "topic": "Mixed martial arts", "parent_topic": "/m/06ntj" },
    { "id": "/m/0410tth", "topic": "Motorsport", "parent_topic": "/m/06ntj" },
    { "id": "/m/07bs0", "topic": "Tennis", "parent_topic": "/m/06ntj" },
    { "id": "/m/07_53", "topic": "Volleyball", "parent_topic": "/m/06ntj" },

    { "id": "/m/02jjt", "topic": "Entertainment", "parent": true },
    { "id": "/m/09kqc", "topic": "Humor", "parent_topic": "/m/02jjt" },
    { "id": "/m/02vxn", "topic": "Movies", "parent_topic": "/m/02jjt" },
    { "id": "/m/05qjc", "topic": "Performing arts", "parent_topic": "/m/02jjt" },
    { "id": "/m/066wd", "topic": "Professional wrestling", "parent_topic": "/m/02jjt" },
    { "id": "/m/0f2f9", "topic": "TV shows", "parent_topic": "/m/02jjt" },

    { "id": "/m/019_rr", "topic": "Lifestyle", "parent": true },
    { "id": "/m/032tl", "topic": "Fashion", "parent_topic": "/m/019_rr" },
    { "id": "/m/027x7n", "topic": "Fitness", "parent_topic": "/m/019_rr" },
    { "id": "/m/02wbm", "topic": "Food", "parent_topic": "/m/019_rr" },
    { "id": "/m/03glg", "topic": "Hobby", "parent_topic": "/m/019_rr" },
    { "id": "/m/068hy", "topic": "Pets", "parent_topic": "/m/019_rr" },
    { "id": "/m/041xxh", "topic": "Physical attractiveness [Beauty]", "parent_topic": "/m/019_rr" },
    { "id": "/m/07c1v", "topic": "Technology", "parent_topic": "/m/019_rr" },
    { "id": "/m/07bxq", "topic": "Tourism", "parent_topic": "/m/019_rr" },
    { "id": "/m/07yv9", "topic": "Vehicles", "parent_topic": "/m/019_rr" },

    { "id": "/m/098wr", "topic": "Society", "parent": true },
    { "id": "/m/09s1f", "topic": "Business", "parent_topic": "/m/098wr" },
    { "id": "/m/0kt51", "topic": "Health", "parent_topic": "/m/098wr" },
    { "id": "/m/01h6rj", "topic": "Military", "parent_topic": "/m/098wr" },
    { "id": "/m/05qt0", "topic": "Politics", "parent_topic": "/m/098wr" },
    { "id": "/m/06bvp", "topic": "Religion", "parent_topic": "/m/098wr" },

    { "id": "/m/01k8wb", "topic": "Knowledge" }
]
